xldeploy/__init__.py
xldeploy/client.py
xldeploy/config.py
xldeploy/errors.py
xldeploy/domain/ConfigurationItem.py
xldeploy/domain/Deployment.py
xldeploy/domain/QueryBuilder.py
xldeploy/domain/Task.py
xldeploy/domain/__init__.py
xldeploy/http/__init__.py
xldeploy/http/http_client.py
xldeploy/service/__init__.py
xldeploy/service/deployfile.py
xldeploy/service/deployment.py
xldeploy/service/metadata.py
xldeploy/service/package.py
xldeploy/service/repository.py
xldeploy/service/tasks.py
xldeploy/tests/__init__.py
xldeploy/tests/deployfile_test.py
xldeploy/tests/deployment_test.py
xldeploy/tests/metadata_test.py
xldeploy/tests/repository_test.py
xldeploy/tests/tasks_test.py
xldeploy_py-0.0.20.dist-info/LICENSE.txt
xldeploy_py-0.0.20.dist-info/METADATA
xldeploy_py-0.0.20.dist-info/WHEEL
xldeploy_py-0.0.20.dist-info/top_level.txt
xldeploy_py-0.0.20.dist-info/RECORD
