Metadata-Version: 2.1
Name: xldeploy-py
Version: 0.0.20
Summary: The python sdk for xldeploy
Home-page: https://github.com/xebialabs/xldeploy-py
Author: Xebialabs
Author-email: opensource@xebialabs.com
License: MIT
Keywords: xldeploy sdk python xebialabs
License-File: LICENSE.txt
Requires-Dist: requests ==2.31.0
